enviromancer/__init__.py
enviromancer/env_variable.py
enviromancer/enviromancer.py
enviromancer-0.1.7.dist-info/LICENSE
enviromancer-0.1.7.dist-info/METADATA
enviromancer-0.1.7.dist-info/WHEEL
enviromancer-0.1.7.dist-info/RECORD
