Metadata-Version: 2.3
Name: enviromancer
Version: 0.1.7
Summary: Gain mastery over your environment variables
License: LGPL-3.0-or-later
Author: Danny Stewart
Author-email: danny@stewart.cc
Requires-Python: >=3.12
Classifier: Development Status :: 4 - Beta
Classifier: Environment :: Console
Classifier: Intended Audience :: Developers
Classifier: License :: OSI Approved :: GNU Lesser General Public License v3 or later (LGPLv3+)
Classifier: Programming Language :: Python :: 3
Classifier: Programming Language :: Python :: 3.12
Classifier: Programming Language :: Python :: 3.13
Classifier: Topic :: Software Development :: Libraries
Classifier: Topic :: Software Development :: Libraries :: Python Modules
Classifier: Topic :: System :: Shells
Classifier: Topic :: System :: System Shells
Classifier: Topic :: Utilities
Requires-Dist: logician (>=0.3.4)
Requires-Dist: polykit (>=0.1.1)
Requires-Dist: python-dotenv (>=1.1.0)
